tx/__init__.py
tx/ext/__init__.py
tx-0.0.2.dist-info/LICENSE
tx-0.0.2.dist-info/WHEEL
tx-0.0.2.dist-info/METADATA
tx-0.0.2.dist-info/RECORD
