Metadata-Version: 2.1
Name: tx
Version: 0.0.2
Summary: An extension base for twisted based projects
Home-page: UNKNOWN
License: MIT
Author: Yehuda Deutsch
Author-email: yeh@uda.co.il
Requires-Python: >=3.6,<4.0
Classifier: License :: OSI Approved :: MIT License
Classifier: Programming Language :: Python :: 3
Classifier: Programming Language :: Python :: 3.6
Classifier: Programming Language :: Python :: 3.7
Requires-Dist: Twisted (>=18.9,<19.0)
